com/fw/base/base_dao.py
com/fw/base/base_exception.py
com/fw/base/base_log.py
com/fw/base/base_route.py
com/fw/base/base_service.py
com/fw/base/test_dao.py
com/fw/db/mongo_db.py
com/fw/db/mysql_db.py
com/fw/db/page.py
com/fw/db/query.py
com/fw/db/redis_db.py
com/fw/db/update.py
com/fw/routes/test_route.py
com/fw/system/falcon_filter.py
com/fw/system/red_conf.py
com/fw/system/run.py
com/fw/system/socket_server_asgi.py
com/fw/system/socket_server_uwsgi.py
com/fw/system/task.py
com/fw/system/test.py
com/fw/utils/common_utils.py
com/fw/utils/enums_utils.py
com/fw/utils/id_util.py
com/fw/utils/json_serializer.py
com/fw/utils/lock_utils.py
com/fw/utils/time_utils.py
jintian_architecture_code-5.0.dist-info/LICENSE
jintian_architecture_code-5.0.dist-info/METADATA
jintian_architecture_code-5.0.dist-info/WHEEL
jintian_architecture_code-5.0.dist-info/top_level.txt
jintian_architecture_code-5.0.dist-info/RECORD
