Metadata-Version: 2.1
Name: jintian-architecture-code
Version: 5.0
Summary: jintian-architecture-code
Home-page: UNKNOWN
Author: UNKNOWN
Author-email: 767980702@qq.com
License: UNKNOWN
Platform: UNKNOWN
Classifier: Programming Language :: Python :: 3
Classifier: License :: OSI Approved :: MIT License
Classifier: Operating System :: OS Independent
